rhea_sdk/__init__.py
rhea_sdk/constances.py
rhea_sdk/exceptions.py
rhea_sdk/main.py
rhea_sdk/dcl/__init__.py
rhea_sdk/dcl/dcl.py
rhea_sdk/lending/__init__.py
rhea_sdk/lending/lending.py
rhea_sdk/utils/__init__.py
rhea_sdk/utils/fastnear.py
rhea_sdk/v1/__init__.py
rhea_sdk-0.3.0.dist-info/licenses/LICENSE.txt
rhea_sdk-0.3.0.dist-info/METADATA
rhea_sdk-0.3.0.dist-info/WHEEL
rhea_sdk-0.3.0.dist-info/top_level.txt
rhea_sdk-0.3.0.dist-info/RECORD
