Metadata-Version: 2.4
Name: rhea-sdk
Version: 0.3.0
Summary: Asynchronous SDK for interacting with Rhea Finance DEX
Author-email: Maksim_Antsiferov <antsiferov.ms@gmail.com>
Project-URL: homepage, https://github.com/MaximAntsiferov/rhea-sdk
Project-URL: documentation, https://github.com/MaximAntsiferov/rhea-sdk
Project-URL: repository, https://github.com/MaximAntsiferov/rhea-sdk
Project-URL: changelog, https://github.com/MaximAntsiferov/rhea-sdk/blob/main/CHANGELOG.md
Project-URL: twitter, https://twitter.com/MaksimA30
Keywords: python,near,rhea,dex,trading,ref
Classifier: Programming Language :: Python :: 3
Classifier: License :: OSI Approved :: MIT License
Classifier: Operating System :: OS Independent
Requires-Python: >=3
License-File: LICENSE.txt
Requires-Dist: asyncio>=3.4.3
Requires-Dist: py-near>=1.1.57
Dynamic: license-file
